siderpy.py
siderpy-0.7.0.dist-info/LICENSE
siderpy-0.7.0.dist-info/METADATA
siderpy-0.7.0.dist-info/WHEEL
siderpy-0.7.0.dist-info/top_level.txt
siderpy-0.7.0.dist-info/RECORD
