Metadata-Version: 2.1
Name: siderpy
Version: 0.7.0
Summary: Asyncio Redis client
Author: Roma Koshel
Author-email: roma.koshel@gmail.com
License: MIT
Classifier: Development Status :: 2 - Pre-Alpha
Classifier: Programming Language :: Python
Classifier: Programming Language :: Python :: 3
Classifier: Operating System :: POSIX :: Linux
Classifier: Operating System :: MacOS :: MacOS X
Requires-Python: >=3.7
License-File: LICENSE
Provides-Extra: hiredis
Requires-Dist: hiredis ; extra == 'hiredis'
